urlscanner/__init__.py
urlscanner/__main__.py
urlscanner/client.py
urlscanner/iomanager.py
urlscanner/util.py
urlscanner-1.0.dist-info/METADATA
urlscanner-1.0.dist-info/WHEEL
urlscanner-1.0.dist-info/RECORD
