Metadata-Version: 2.1
Name: urlscanner
Version: 1.0
Summary: Lightweight Python CLI utility which makes use URLScan.io APIs to automate scanning and retrieving information about URLs
Project-URL: Homepage, https://github.com/birkagal/urlscanner
Project-URL: Bug Tracker, https://github.com/birkagal/urlscanner/issues
Author-email: Gal Birka <birkagal@gmail.com>
Classifier: License :: OSI Approved :: MIT License
Classifier: Operating System :: OS Independent
Classifier: Programming Language :: Python :: 3
Requires-Python: >=3.7
Requires-Dist: python-dotenv
Requires-Dist: requests
